camera_ui_rpc_client/__init__.py
camera_ui_rpc_client/__init__.pyi
camera_ui_rpc_client/constants.py
camera_ui_rpc_client/constants.pyi
camera_ui_rpc_client/py.typed
camera_ui_rpc_client/typings.py
camera_ui_rpc_client/typings.pyi
camera_ui_rpc_client-0.0.1.dist-info/LICENSE.md
camera_ui_rpc_client-0.0.1.dist-info/METADATA
camera_ui_rpc_client-0.0.1.dist-info/WHEEL
camera_ui_rpc_client-0.0.1.dist-info/top_level.txt
camera_ui_rpc_client-0.0.1.dist-info/RECORD
